[
  {
    "eventPlace": "Le Sucre",
    "city": "Lyon",
    "country": "France",
    "eventDate": "Archives",
    "eventStyle": "Electro",
    "eventName": "Retrouvez tous nos événements passés,",
    "isCancelled": false,
    "eventURL": "https://le-sucre.eu/agenda-archives/",
    "eventDetailedStyle": "",
    "source": {
      "name": "Le Sucre",
      "city": "Lyon",
      "country": "France"
    },
    "unixDate": 0,
    "errorLog": "Format de date invalide pour Le Sucre. Reçu 'Archives', converti en ''. Formats essayés: dd-MM"
  },
  {
    "eventPlace": "Le Sonic",
    "city": "Lyon",
    "country": "France",
    "eventName": "EL Gant + vinyl dj set",
    "eventDate": "mercredi 15.10.25",
    "eventURL": "https://sonic-lyon.fr/evenement/el-gant-vinyl-dj-set/",
    "isCancelled": false,
    "eventDetailedStyle": "",
    "eventStyle": "Rock",
    "source": {
      "name": "Le Sonic",
      "city": "Lyon",
      "country": "France"
    },
    "unixDate": 0,
    "errorLog": "Format de date invalide pour Le Sonic. Reçu 'mercredi 15.10.25', converti en '15-10-25'. Formats essayés: dd-MM-yy-HH:mm"
  },
  {
    "eventPlace": "Auditorium de Lyon",
    "city": "Lyon",
    "country": "France",
    "eventName": "Histoires en musique",
    "eventURL": "https://www.petit-bulletin.fr/agenda-315943-histoires-en-musique.html",
    "eventStyle": "Classique",
    "eventDate": "21 octobre et 22 octobre à 11h et 15h",
    "isCancelled": false,
    "eventDetailedStyle": "(Classique et Lyrique)",
    "source": {
      "name": "Le Petit Bulletin",
      "city": "Lyon",
      "country": "France"
    },
    "unixDate": 0,
    "errorLog": "Format de date invalide pour Le Petit Bulletin. Reçu '21 octobre et 22 octobre à 11h et 15h', converti en '21-10-22-11:00'. Formats essayés: dd-MM-yyyy-HH:mm"
  },
  {
    "eventPlace": "Opéra National de Lyon",
    "city": "Lyon",
    "country": "France",
    "eventName": "Boris Godounov",
    "eventURL": "https://www.petit-bulletin.fr/agenda-315641-boris-godounov.html",
    "eventStyle": "Classique",
    "eventDate": "Du 13 au 25 octobre 2025, à 20h sauf dimanche à 16h",
    "isCancelled": false,
    "eventDetailedStyle": "(Classique et Lyrique)",
    "source": {
      "name": "Le Petit Bulletin",
      "city": "Lyon",
      "country": "France"
    },
    "unixDate": 0,
    "errorLog": "Format de date invalide pour Le Petit Bulletin. Reçu 'Du 13 au 25 octobre 2025, à 20h sauf dimanche à 16h', converti en '13-25-10-2025-20:00'. Formats essayés: dd-MM-yyyy-HH:mm"
  },
  {
    "eventPlace": "Auditorium de Lyon",
    "city": "Lyon",
    "country": "France",
    "eventName": "Journées du piano",
    "eventURL": "https://www.petit-bulletin.fr/agenda-315642-journees-du-piano.html",
    "eventStyle": "Classique",
    "eventDate": "Du 20 au 22 novembre 2025, jeudi et vendredi à 20h, samedi à 11h, 15h et 18h",
    "isCancelled": false,
    "eventDetailedStyle": "(Classique et Lyrique)",
    "source": {
      "name": "Le Petit Bulletin",
      "city": "Lyon",
      "country": "France"
    },
    "unixDate": 0,
    "errorLog": "Format de date invalide pour Le Petit Bulletin. Reçu 'Du 20 au 22 novembre 2025, jeudi et vendredi à 20h, samedi à 11h, 15h et 18h', converti en '20-22-11-2025-20:00-15:00-18:00'. Formats essayés: dd-MM-yyyy-HH:mm"
  },
  {
    "eventPlace": "Le Sucre",
    "city": "Lyon",
    "country": "France",
    "eventName": "Square festival",
    "eventURL": "https://www.petit-bulletin.fr/agenda-315315-square-festival.html",
    "eventStyle": "Live",
    "eventDate": "Du 9 au 14 décembre 2025, horaires et tarifs à venir",
    "isCancelled": false,
    "eventDetailedStyle": "(Musique Electronique)",
    "source": {
      "name": "Le Petit Bulletin",
      "city": "Lyon",
      "country": "France"
    },
    "unixDate": 0,
    "errorLog": "Format de date invalide pour Le Petit Bulletin. Reçu 'Du 9 au 14 décembre 2025, horaires et tarifs à venir', converti en '09-14-12-2025'. Formats essayés: dd-MM-yyyy-HH:mm"
  },
  {
    "eventPlace": "Auditorium de Lyon",
    "city": "Lyon",
    "country": "France",
    "eventName": "L'amour et la mer",
    "eventURL": "https://www.petit-bulletin.fr/agenda-315643-l-amour-et-la-mer.html",
    "eventStyle": "Classique",
    "eventDate": "Du 18 au 20 décembre 2025, jeudi à 20h, samedi à 18h",
    "isCancelled": false,
    "eventDetailedStyle": "(Classique et Lyrique)",
    "source": {
      "name": "Le Petit Bulletin",
      "city": "Lyon",
      "country": "France"
    },
    "unixDate": 0,
    "errorLog": "Format de date invalide pour Le Petit Bulletin. Reçu 'Du 18 au 20 décembre 2025, jeudi à 20h, samedi à 18h', converti en '18-20-12-2025-20:00'. Formats essayés: dd-MM-yyyy-HH:mm"
  },
  {
    "eventPlace": "Marché Gare",
    "city": "Lyon",
    "country": "France",
    "isCancelled": false,
    "eventURL": "https://marchegare.fr/agenda/lyonburlesquefestival2025-pass",
    "eventName": "LYON BURLESQUE FESTIVAL - Pass 2 jours ,",
    "eventDate": "14. 15. 11 2025",
    "eventDetailedStyle": "",
    "eventStyle": "Live",
    "source": {
      "name": "Marché Gare",
      "city": "Lyon",
      "country": "France"
    },
    "unixDate": 0,
    "errorLog": "Format de date invalide pour Marché Gare. Reçu '14. 15. 11 2025', converti en '14-15-11-2025'. Formats essayés: dd-MM-yyyy"
  },
  {
    "eventPlace": "Théâtre de l'Élysée",
    "city": "Lyon",
    "country": "France",
    "eventName": "LA FAUSSE SUIVANTE - D’après l’œuvre de Marivaux / Cie L’Imposture",
    "eventDate": "Tuesday, Oct 14, 07:30 PM → Friday, Oct 17",
    "eventURL": "https://villemorte.fr/tag/th%C3%A9%C3%A2tre",
    "isCancelled": false,
    "eventDetailedStyle": "",
    "eventStyle": "Live",
    "source": {
      "name": "Ville Morte",
      "city": "Lyon",
      "country": "France"
    },
    "unixDate": 0,
    "errorLog": "Format de date invalide pour Ville Morte. Reçu 'Tuesday, Oct 14, 07:30 PM → Friday, Oct 17', converti en '10-14-07:30-17'. Formats essayés: MM-dd-HH:mm"
  },
  {
    "eventPlace": "Théâtre de l'Élysée",
    "city": "Lyon",
    "country": "France",
    "eventName": "FACT - Festival Arts et Créations Trans",
    "eventDate": "Tuesday, Oct 21, 07:00 PM → Sunday, Oct 26",
    "eventURL": "https://villemorte.fr/tag/th%C3%A9%C3%A2tre",
    "isCancelled": false,
    "eventDetailedStyle": "",
    "eventStyle": "Live",
    "source": {
      "name": "Ville Morte",
      "city": "Lyon",
      "country": "France"
    },
    "unixDate": 0,
    "errorLog": "Format de date invalide pour Ville Morte. Reçu 'Tuesday, Oct 21, 07:00 PM → Sunday, Oct 26', converti en '10-21-07:00-26'. Formats essayés: MM-dd-HH:mm"
  },
  {
    "eventPlace": "Espace Gerson",
    "city": "Lyon",
    "country": "France",
    "eventName": "MAGALI GIO",
    "eventURL": "https://www.infoconcert.com/ticket/concert-magali-gio-lyon/1778671.html",
    "isCancelled": false,
    "eventDate": "22",
    "eventDetailedStyle": "",
    "eventStyle": "Theatre",
    "source": {
      "name": "Infoconcert",
      "city": "Lyon",
      "country": "France"
    },
    "unixDate": 0,
    "errorLog": "Format de date invalide pour Infoconcert. Reçu '22', converti en '22'. Formats essayés: dd-MM-yyyy-HH:mm"
  },
  {
    "eventPlace": "La Rayonne",
    "city": "Lyon",
    "country": "France",
    "eventDate": "dimanche 26 octobre 2025",
    "isCancelled": false,
    "eventName": "RevPro : Live in Lyon - In association with LWA",
    "eventURL": "https://larayonne.org/evenement/revpro-live-in-lyon/",
    "eventDetailedStyle": "",
    "eventStyle": "Live",
    "source": {
      "name": "La Rayonne",
      "city": "Lyon",
      "country": "France"
    },
    "unixDate": 0,
    "errorLog": "Format de date invalide pour La Rayonne. Reçu 'dimanche 26 octobre 2025', converti en '26-10-2025'. Formats essayés: dd-MM-yyyy-HH:mm, dd-MM-HH:mm"
  },
  {
    "eventPlace": "LDLC Arena",
    "city": "Lyon",
    "country": "France",
    "eventName": "SOPRANO",
    "eventDate": "1er et 2 novembre 2025",
    "eventURL": "https://www.olvallee.fr/evenement/soprano-lyon-2025/",
    "isCancelled": false,
    "eventDetailedStyle": "",
    "eventStyle": "Live",
    "source": {
      "name": "LDLC Arena",
      "city": "Lyon",
      "country": "France"
    },
    "unixDate": 0,
    "errorLog": "Format de date invalide pour LDLC Arena. Reçu '1er et 2 novembre 2025', converti en '01er-02-11-2025'. Formats essayés: dd-MM-yyyy-HH:mm"
  },
  {
    "eventPlace": "LDLC Arena",
    "city": "Lyon",
    "country": "France",
    "eventName": "LADY GAGA",
    "eventDate": "13 et 14 novembre 2025",
    "eventURL": "https://www.olvallee.fr/evenement/lady-gaga-lyon-2025/",
    "isCancelled": false,
    "eventDetailedStyle": "",
    "eventStyle": "Live",
    "source": {
      "name": "LDLC Arena",
      "city": "Lyon",
      "country": "France"
    },
    "unixDate": 0,
    "errorLog": "Format de date invalide pour LDLC Arena. Reçu '13 et 14 novembre 2025', converti en '13-14-11-2025'. Formats essayés: dd-MM-yyyy-HH:mm"
  },
  {
    "eventPlace": "LDLC Arena",
    "city": "Lyon",
    "country": "France",
    "eventName": "GIMS",
    "eventDate": "25, 26, 27 et 28 novembre 2025",
    "eventURL": "https://www.olvallee.fr/evenement/gims-2025-lyon-2/",
    "isCancelled": false,
    "eventDetailedStyle": "",
    "eventStyle": "Live",
    "source": {
      "name": "LDLC Arena",
      "city": "Lyon",
      "country": "France"
    },
    "unixDate": 0,
    "errorLog": "Format de date invalide pour LDLC Arena. Reçu '25, 26, 27 et 28 novembre 2025', converti en '25-26-27-28-11-2025'. Formats essayés: dd-MM-yyyy-HH:mm"
  },
  {
    "eventPlace": "LDLC Arena",
    "city": "Lyon",
    "country": "France",
    "eventName": "Orelsan",
    "eventDate": "26 et 27 février 2026",
    "eventURL": "https://www.olvallee.fr/evenement/orelsan-lyon-2026/",
    "isCancelled": false,
    "eventDetailedStyle": "",
    "eventStyle": "Live",
    "source": {
      "name": "LDLC Arena",
      "city": "Lyon",
      "country": "France"
    },
    "unixDate": 0,
    "errorLog": "Format de date invalide pour LDLC Arena. Reçu '26 et 27 février 2026', converti en '26-27-02-2026'. Formats essayés: dd-MM-yyyy-HH:mm"
  },
  {
    "eventPlace": "LDLC Arena",
    "city": "Lyon",
    "country": "France",
    "eventName": "Florent Pagny",
    "eventDate": "18, 19, 21 et 22 mars 2026",
    "eventURL": "https://www.olvallee.fr/evenement/florent-pagny-lyon-2026/",
    "isCancelled": false,
    "eventDetailedStyle": "",
    "eventStyle": "Live",
    "source": {
      "name": "LDLC Arena",
      "city": "Lyon",
      "country": "France"
    },
    "unixDate": 0,
    "errorLog": "Format de date invalide pour LDLC Arena. Reçu '18, 19, 21 et 22 mars 2026', converti en '18-19-21-22-03-2026'. Formats essayés: dd-MM-yyyy-HH:mm"
  },
  {
    "eventPlace": "LDLC Arena",
    "city": "Lyon",
    "country": "France",
    "eventName": "LINKIN PARK",
    "eventDate": "16 juin 2026",
    "eventURL": "https://www.olvallee.fr/evenement/linkin-park-lyon-2026/",
    "isCancelled": false,
    "eventDetailedStyle": "",
    "eventStyle": "Live",
    "source": {
      "name": "LDLC Arena",
      "city": "Lyon",
      "country": "France"
    },
    "unixDate": 0,
    "errorLog": "Format de date invalide pour LDLC Arena. Reçu '16 juin 2026', converti en '16-06-2026'. Formats essayés: dd-MM-yyyy-HH:mm"
  },
  {
    "eventPlace": "LDLC Arena",
    "city": "Lyon",
    "country": "France",
    "eventName": "IRON MAIDEN",
    "eventDate": "28 juin 2026",
    "eventURL": "https://www.olvallee.fr/evenement/iron-maiden-lyon-2026/",
    "isCancelled": false,
    "eventDetailedStyle": "",
    "eventStyle": "Live",
    "source": {
      "name": "LDLC Arena",
      "city": "Lyon",
      "country": "France"
    },
    "unixDate": 0,
    "errorLog": "Format de date invalide pour LDLC Arena. Reçu '28 juin 2026', converti en '28-06-2026'. Formats essayés: dd-MM-yyyy-HH:mm"
  },
  {
    "eventPlace": "Radiant-Bellevue",
    "city": "Lyon",
    "country": "France",
    "eventStyle": "Live",
    "eventName": "Stomp",
    "eventDate": "16,17,18,19 octobre 2025",
    "isCancelled": false,
    "eventURL": "https://radiant-bellevue.fr/spectacles/stomp-2/",
    "eventDetailedStyle": "Musique - Danse",
    "source": {
      "name": "Radiant-Bellevue",
      "city": "Lyon",
      "country": "France"
    },
    "unixDate": 0,
    "errorLog": "Format de date invalide pour Radiant-Bellevue. Reçu '16,17,18,19 octobre 2025', converti en '16-17-18-19-10-2025'. Formats essayés: dd-MM-yyyy"
  },
  {
    "eventPlace": "Radiant-Bellevue",
    "city": "Lyon",
    "country": "France",
    "eventStyle": "Live",
    "eventName": "Sofiane Pamart",
    "eventDate": "06, 07 & 08 novembre 2025",
    "isCancelled": false,
    "eventURL": "https://radiant-bellevue.fr/spectacles/sofiane-pamart/",
    "eventDetailedStyle": "Musique",
    "source": {
      "name": "Radiant-Bellevue",
      "city": "Lyon",
      "country": "France"
    },
    "unixDate": 0,
    "errorLog": "Format de date invalide pour Radiant-Bellevue. Reçu '06, 07 & 08 novembre 2025', converti en '06-07-08-11-2025'. Formats essayés: dd-MM-yyyy"
  },
  {
    "eventPlace": "Radiant-Bellevue",
    "city": "Lyon",
    "country": "France",
    "eventStyle": "Live",
    "eventName": "Comme ça vous chante !",
    "eventDate": "10 & 11 novembre 2025",
    "isCancelled": false,
    "eventURL": "https://radiant-bellevue.fr/spectacles/comme-ca-vous-chante/",
    "eventDetailedStyle": "Musique",
    "source": {
      "name": "Radiant-Bellevue",
      "city": "Lyon",
      "country": "France"
    },
    "unixDate": 0,
    "errorLog": "Format de date invalide pour Radiant-Bellevue. Reçu '10 & 11 novembre 2025', converti en '10-11-11-2025'. Formats essayés: dd-MM-yyyy"
  },
  {
    "eventPlace": "Radiant-Bellevue",
    "city": "Lyon",
    "country": "France",
    "eventStyle": "Chanson",
    "eventName": "Hoshi",
    "eventDate": "22 & 23 novembre 25",
    "isCancelled": false,
    "eventURL": "https://radiant-bellevue.fr/spectacles/hoshi/",
    "eventDetailedStyle": "Musique - Chanson",
    "source": {
      "name": "Radiant-Bellevue",
      "city": "Lyon",
      "country": "France"
    },
    "unixDate": 0,
    "errorLog": "Format de date invalide pour Radiant-Bellevue. Reçu '22 & 23 novembre 25', converti en '22-23-11-25'. Formats essayés: dd-MM-yyyy"
  },
  {
    "eventPlace": "Radiant-Bellevue",
    "city": "Lyon",
    "country": "France",
    "eventStyle": "Théâtre",
    "eventName": "La Famille",
    "eventDate": "27 & 28 novembre 2025",
    "isCancelled": false,
    "eventURL": "https://radiant-bellevue.fr/spectacles/la-famille/",
    "eventDetailedStyle": "Théâtre",
    "source": {
      "name": "Radiant-Bellevue",
      "city": "Lyon",
      "country": "France"
    },
    "unixDate": 0,
    "errorLog": "Format de date invalide pour Radiant-Bellevue. Reçu '27 & 28 novembre 2025', converti en '27-28-11-2025'. Formats essayés: dd-MM-yyyy"
  },
  {
    "eventPlace": "Radiant-Bellevue",
    "city": "Lyon",
    "country": "France",
    "eventStyle": "Théâtre",
    "eventName": "Le Misanthrope",
    "eventDate": "02 & 03 décembre 2025",
    "isCancelled": false,
    "eventURL": "https://radiant-bellevue.fr/spectacles/le-misanthrope/",
    "eventDetailedStyle": "Théâtre",
    "source": {
      "name": "Radiant-Bellevue",
      "city": "Lyon",
      "country": "France"
    },
    "unixDate": 0,
    "errorLog": "Format de date invalide pour Radiant-Bellevue. Reçu '02 & 03 décembre 2025', converti en '02-03-12-2025'. Formats essayés: dd-MM-yyyy"
  },
  {
    "eventPlace": "Radiant-Bellevue",
    "city": "Lyon",
    "country": "France",
    "eventStyle": "Danse",
    "eventName": "Victoria Dauberville",
    "eventDate": "07 & 08 décembre 2025",
    "isCancelled": false,
    "eventURL": "https://radiant-bellevue.fr/spectacles/victoria-dauberville/",
    "eventDetailedStyle": "Danse",
    "source": {
      "name": "Radiant-Bellevue",
      "city": "Lyon",
      "country": "France"
    },
    "unixDate": 0,
    "errorLog": "Format de date invalide pour Radiant-Bellevue. Reçu '07 & 08 décembre 2025', converti en '07-08-12-2025'. Formats essayés: dd-MM-yyyy"
  },
  {
    "eventPlace": "Radiant-Bellevue",
    "city": "Lyon",
    "country": "France",
    "eventStyle": "Théâtre",
    "eventName": "Le duplex",
    "eventDate": "18 & 19 décembre 2025",
    "isCancelled": false,
    "eventURL": "https://radiant-bellevue.fr/spectacles/le-duplex/",
    "eventDetailedStyle": "Théâtre",
    "source": {
      "name": "Radiant-Bellevue",
      "city": "Lyon",
      "country": "France"
    },
    "unixDate": 0,
    "errorLog": "Format de date invalide pour Radiant-Bellevue. Reçu '18 & 19 décembre 2025', converti en '18-19-12-2025'. Formats essayés: dd-MM-yyyy"
  },
  {
    "eventPlace": "Radiant-Bellevue",
    "city": "Lyon",
    "country": "France",
    "eventStyle": "Théâtre",
    "eventName": "FABRICE LUCHINI",
    "eventDate": "22 & 23 décembre 2025",
    "isCancelled": false,
    "eventURL": "https://radiant-bellevue.fr/spectacles/fabrice-luchini-2/",
    "eventDetailedStyle": "Théâtre",
    "source": {
      "name": "Radiant-Bellevue",
      "city": "Lyon",
      "country": "France"
    },
    "unixDate": 0,
    "errorLog": "Format de date invalide pour Radiant-Bellevue. Reçu '22 & 23 décembre 2025', converti en '22-23-12-2025'. Formats essayés: dd-MM-yyyy"
  },
  {
    "eventPlace": "Radiant-Bellevue",
    "city": "Lyon",
    "country": "France",
    "eventStyle": "Théâtre",
    "eventName": "Mon jour de chance",
    "eventDate": "15 & 16 janvier 2026",
    "isCancelled": false,
    "eventURL": "https://radiant-bellevue.fr/spectacles/mon-jour-de-chance/",
    "eventDetailedStyle": "Théâtre",
    "source": {
      "name": "Radiant-Bellevue",
      "city": "Lyon",
      "country": "France"
    },
    "unixDate": 0,
    "errorLog": "Format de date invalide pour Radiant-Bellevue. Reçu '15 & 16 janvier 2026', converti en '15-16-01-2026'. Formats essayés: dd-MM-yyyy"
  },
  {
    "eventPlace": "Radiant-Bellevue",
    "city": "Lyon",
    "country": "France",
    "eventStyle": "Théâtre - Immanquable",
    "eventName": "Le repas des gens",
    "eventDate": "27 & 28 janvier 2026",
    "isCancelled": false,
    "eventURL": "https://radiant-bellevue.fr/spectacles/le-repas-des-gens/",
    "eventDetailedStyle": "Théâtre - Immanquable",
    "source": {
      "name": "Radiant-Bellevue",
      "city": "Lyon",
      "country": "France"
    },
    "unixDate": 0,
    "errorLog": "Format de date invalide pour Radiant-Bellevue. Reçu '27 & 28 janvier 2026', converti en '27-28-01-2026'. Formats essayés: dd-MM-yyyy"
  },
  {
    "eventPlace": "Radiant-Bellevue",
    "city": "Lyon",
    "country": "France",
    "eventStyle": "Théâtre",
    "eventName": "lily et lily",
    "eventDate": "01 & 02 février 2026",
    "isCancelled": false,
    "eventURL": "https://radiant-bellevue.fr/spectacles/lily-et-lily/",
    "eventDetailedStyle": "Théâtre",
    "source": {
      "name": "Radiant-Bellevue",
      "city": "Lyon",
      "country": "France"
    },
    "unixDate": 0,
    "errorLog": "Format de date invalide pour Radiant-Bellevue. Reçu '01 & 02 février 2026', converti en '01-02-02-2026'. Formats essayés: dd-MM-yyyy"
  },
  {
    "eventPlace": "Radiant-Bellevue",
    "city": "Lyon",
    "country": "France",
    "eventStyle": "Cirque - Famille",
    "eventName": "Wolf",
    "eventDate": "06 & 07 février 2026",
    "isCancelled": false,
    "eventURL": "https://radiant-bellevue.fr/spectacles/wolf/",
    "eventDetailedStyle": "Cirque - Famille",
    "source": {
      "name": "Radiant-Bellevue",
      "city": "Lyon",
      "country": "France"
    },
    "unixDate": 0,
    "errorLog": "Format de date invalide pour Radiant-Bellevue. Reçu '06 & 07 février 2026', converti en '06-07-02-2026'. Formats essayés: dd-MM-yyyy"
  },
  {
    "eventPlace": "Radiant-Bellevue",
    "city": "Lyon",
    "country": "France",
    "eventStyle": "Théâtre",
    "eventName": "DU CHARBON DANS LES VEINES",
    "eventDate": "23 & 24 février 2026",
    "isCancelled": false,
    "eventURL": "https://radiant-bellevue.fr/spectacles/du-charbon-dans-les-veines/",
    "eventDetailedStyle": "Théâtre",
    "source": {
      "name": "Radiant-Bellevue",
      "city": "Lyon",
      "country": "France"
    },
    "unixDate": 0,
    "errorLog": "Format de date invalide pour Radiant-Bellevue. Reçu '23 & 24 février 2026', converti en '23-24-02-2026'. Formats essayés: dd-MM-yyyy"
  },
  {
    "eventPlace": "Radiant-Bellevue",
    "city": "Lyon",
    "country": "France",
    "eventStyle": "Théâtre",
    "eventName": "CYRANO DE BERGERAC",
    "eventDate": "26 & 27 février 2026",
    "isCancelled": false,
    "eventURL": "https://radiant-bellevue.fr/spectacles/cyrano-de-bergerac/",
    "eventDetailedStyle": "Théâtre",
    "source": {
      "name": "Radiant-Bellevue",
      "city": "Lyon",
      "country": "France"
    },
    "unixDate": 0,
    "errorLog": "Format de date invalide pour Radiant-Bellevue. Reçu '26 & 27 février 2026', converti en '26-27-02-2026'. Formats essayés: dd-MM-yyyy"
  },
  {
    "eventPlace": "Radiant-Bellevue",
    "city": "Lyon",
    "country": "France",
    "eventStyle": "Chanson",
    "eventName": "LAURENT VOULZY",
    "eventDate": "10 & 11 mars 2026",
    "isCancelled": false,
    "eventURL": "https://radiant-bellevue.fr/spectacles/laurent-voulzy/",
    "eventDetailedStyle": "Musique - Chanson",
    "source": {
      "name": "Radiant-Bellevue",
      "city": "Lyon",
      "country": "France"
    },
    "unixDate": 0,
    "errorLog": "Format de date invalide pour Radiant-Bellevue. Reçu '10 & 11 mars 2026', converti en '10-11-03-2026'. Formats essayés: dd-MM-yyyy"
  },
  {
    "eventPlace": "Radiant-Bellevue",
    "city": "Lyon",
    "country": "France",
    "eventStyle": "Théâtre",
    "eventName": "La Vérité",
    "eventDate": "14 mars et 5 mai 2026",
    "isCancelled": false,
    "eventURL": "https://radiant-bellevue.fr/spectacles/la-verite/",
    "eventDetailedStyle": "Théâtre",
    "source": {
      "name": "Radiant-Bellevue",
      "city": "Lyon",
      "country": "France"
    },
    "unixDate": 0,
    "errorLog": "Format de date invalide pour Radiant-Bellevue. Reçu '14 mars et 5 mai 2026', converti en '14-03-05-05-2026'. Formats essayés: dd-MM-yyyy"
  },
  {
    "eventPlace": "Radiant-Bellevue",
    "city": "Lyon",
    "country": "France",
    "eventStyle": "Théâtre - Immanquable",
    "eventName": "Dans les yeux de Monet",
    "eventDate": "22 & 23 mars 2026",
    "isCancelled": false,
    "eventURL": "https://radiant-bellevue.fr/spectacles/dans-les-yeux-de-monet/",
    "eventDetailedStyle": "Théâtre - Immanquable",
    "source": {
      "name": "Radiant-Bellevue",
      "city": "Lyon",
      "country": "France"
    },
    "unixDate": 0,
    "errorLog": "Format de date invalide pour Radiant-Bellevue. Reçu '22 & 23 mars 2026', converti en '22-23-03-2026'. Formats essayés: dd-MM-yyyy"
  },
  {
    "eventPlace": "Radiant-Bellevue",
    "city": "Lyon",
    "country": "France",
    "eventStyle": "Humour",
    "eventName": "Coupe du monde d’impro F.F.F.",
    "eventDate": "27 & 28 mars 2026",
    "isCancelled": false,
    "eventURL": "https://radiant-bellevue.fr/spectacles/coupe-du-monde-dimpro-f-f-f-2/",
    "eventDetailedStyle": "Humour",
    "source": {
      "name": "Radiant-Bellevue",
      "city": "Lyon",
      "country": "France"
    },
    "unixDate": 0,
    "errorLog": "Format de date invalide pour Radiant-Bellevue. Reçu '27 & 28 mars 2026', converti en '27-28-03-2026'. Formats essayés: dd-MM-yyyy"
  },
  {
    "eventPlace": "Radiant-Bellevue",
    "city": "Lyon",
    "country": "France",
    "eventStyle": "Danse",
    "eventName": "KALEIDOSCOPE",
    "eventDate": "01, 02 & 03 avril 2026",
    "isCancelled": false,
    "eventURL": "https://radiant-bellevue.fr/spectacles/kaleidoscope/",
    "eventDetailedStyle": "Danse",
    "source": {
      "name": "Radiant-Bellevue",
      "city": "Lyon",
      "country": "France"
    },
    "unixDate": 0,
    "errorLog": "Format de date invalide pour Radiant-Bellevue. Reçu '01, 02 & 03 avril 2026', converti en '01-02-03-04-2026'. Formats essayés: dd-MM-yyyy"
  },
  {
    "eventPlace": "Radiant-Bellevue",
    "city": "Lyon",
    "country": "France",
    "eventStyle": "Théâtre - Immanquable",
    "eventName": "MÉNOPAUSE",
    "eventDate": "20 & 21 avril 2026",
    "isCancelled": false,
    "eventURL": "https://radiant-bellevue.fr/spectacles/menopause/",
    "eventDetailedStyle": "Théâtre - Immanquable",
    "source": {
      "name": "Radiant-Bellevue",
      "city": "Lyon",
      "country": "France"
    },
    "unixDate": 0,
    "errorLog": "Format de date invalide pour Radiant-Bellevue. Reçu '20 & 21 avril 2026', converti en '20-21-04-2026'. Formats essayés: dd-MM-yyyy"
  },
  {
    "eventPlace": "Radiant-Bellevue",
    "city": "Lyon",
    "country": "France",
    "eventStyle": "Théâtre - Scolaires",
    "eventName": "Comme une image",
    "eventDate": "27 & 28 avril 2026",
    "isCancelled": false,
    "eventURL": "https://radiant-bellevue.fr/spectacles/comme-une-image/",
    "eventDetailedStyle": "Théâtre - Scolaires",
    "source": {
      "name": "Radiant-Bellevue",
      "city": "Lyon",
      "country": "France"
    },
    "unixDate": 0,
    "errorLog": "Format de date invalide pour Radiant-Bellevue. Reçu '27 & 28 avril 2026', converti en '27-28-04-2026'. Formats essayés: dd-MM-yyyy"
  },
  {
    "eventPlace": "Radiant-Bellevue",
    "city": "Lyon",
    "country": "France",
    "eventStyle": "Humour",
    "eventName": "MOGUIZ",
    "eventDate": "06 & 07 mai 2026",
    "isCancelled": false,
    "eventURL": "https://radiant-bellevue.fr/spectacles/moguiz/",
    "eventDetailedStyle": "Humour",
    "source": {
      "name": "Radiant-Bellevue",
      "city": "Lyon",
      "country": "France"
    },
    "unixDate": 0,
    "errorLog": "Format de date invalide pour Radiant-Bellevue. Reçu '06 & 07 mai 2026', converti en '06-07-05-2026'. Formats essayés: dd-MM-yyyy"
  },
  {
    "eventPlace": "Radiant-Bellevue",
    "city": "Lyon",
    "country": "France",
    "eventStyle": "Théâtre - Scolaires",
    "eventName": "Bleu Nuit",
    "eventDate": "11 & 12 mai 2026",
    "isCancelled": false,
    "eventURL": "https://radiant-bellevue.fr/spectacles/bleu-nuit/",
    "eventDetailedStyle": "Théâtre - Scolaires",
    "source": {
      "name": "Radiant-Bellevue",
      "city": "Lyon",
      "country": "France"
    },
    "unixDate": 0,
    "errorLog": "Format de date invalide pour Radiant-Bellevue. Reçu '11 & 12 mai 2026', converti en '11-12-05-2026'. Formats essayés: dd-MM-yyyy"
  },
  {
    "eventPlace": "Radiant-Bellevue",
    "city": "Lyon",
    "country": "France",
    "eventStyle": "Théâtre - Scolaires",
    "eventName": "Les intempéries de Sami",
    "eventDate": "18 & 19 mai 2026",
    "isCancelled": false,
    "eventURL": "https://radiant-bellevue.fr/spectacles/les-intemperies-de-sami/",
    "eventDetailedStyle": "Théâtre - Scolaires",
    "source": {
      "name": "Radiant-Bellevue",
      "city": "Lyon",
      "country": "France"
    },
    "unixDate": 0,
    "errorLog": "Format de date invalide pour Radiant-Bellevue. Reçu '18 & 19 mai 2026', converti en '18-19-05-2026'. Formats essayés: dd-MM-yyyy"
  },
  {
    "eventPlace": "Les SUBS",
    "city": "Lyon",
    "country": "France",
    "isCancelled": false,
    "eventDetailedStyle": "",
    "eventStyle": "Live",
    "source": {
      "name": "Les SUBS",
      "city": "Lyon",
      "country": "France"
    },
    "unixDate": -1,
    "errorLog": "Pas de date trouvée pour Les SUBS."
  },
  {
    "eventPlace": "Shotgun",
    "city": "Lyon",
    "country": "France",
    "isCancelled": false,
    "eventURL": "https://www.cookiebot.com/en/what-is-behind-powered-by-cookiebot/",
    "eventDetailedStyle": "",
    "eventStyle": "Live",
    "source": {
      "name": "Shotgun",
      "city": "Lyon",
      "country": "France"
    },
    "unixDate": -1,
    "errorLog": "Pas de date trouvée pour Shotgun."
  },
  {
    "eventPlace": "Shotgun",
    "city": "Lyon",
    "country": "France",
    "isCancelled": false,
    "eventURL": "https://shotgun.live/fr/events/theodora-lyon",
    "eventDetailedStyle": "",
    "eventStyle": "Live",
    "source": {
      "name": "Shotgun",
      "city": "Lyon",
      "country": "France"
    },
    "unixDate": -1,
    "errorLog": "Pas de date trouvée pour Shotgun."
  },
  {
    "eventPlace": "HEAT Lyon",
    "city": "Lyon",
    "country": "France",
    "eventName": "[Lyon] Friperie + Dj-Sets + Designers — Stock Xxxxxl",
    "eventDate": "11",
    "isCancelled": false,
    "eventURL": "https://shotgun.live/fr/events/lyon-friperie-dj-sets-designers-stock-xxxxxl",
    "eventDetailedStyle": "",
    "eventStyle": "Live",
    "source": {
      "name": "Shotgun",
      "city": "Lyon",
      "country": "France"
    },
    "unixDate": 0,
    "errorLog": "Format de date invalide pour Shotgun. Reçu '11', converti en '11'. Formats essayés: dd-MM-HH:mm"
  },
  {
    "eventPlace": "La Rayonne",
    "city": "Lyon",
    "country": "France",
    "eventName": "Xlr Events Pres. Th;En + Jast",
    "eventDate": "15",
    "eventStyle": "Electro",
    "isCancelled": false,
    "eventURL": "https://shotgun.live/fr/events/xlr-events-pres-th-en-jast",
    "eventDetailedStyle": "Techno",
    "source": {
      "name": "Shotgun",
      "city": "Lyon",
      "country": "France"
    },
    "unixDate": 0,
    "errorLog": "Format de date invalide pour Shotgun. Reçu '15', converti en '15'. Formats essayés: dd-MM-HH:mm"
  },
  {
    "eventPlace": "Shotgun",
    "city": "Lyon",
    "country": "France",
    "isCancelled": false,
    "eventURL": "https://shotgun.live/fr/artists/theodora",
    "eventDetailedStyle": "",
    "eventStyle": "Live",
    "source": {
      "name": "Shotgun",
      "city": "Lyon",
      "country": "France"
    },
    "unixDate": -1,
    "errorLog": "Pas de date trouvée pour Shotgun."
  },
  {
    "eventPlace": "Shotgun",
    "city": "Lyon",
    "country": "France",
    "isCancelled": false,
    "eventURL": "https://shotgun.live/fr/artists/keblack",
    "eventDetailedStyle": "",
    "eventStyle": "Live",
    "source": {
      "name": "Shotgun",
      "city": "Lyon",
      "country": "France"
    },
    "unixDate": -1,
    "errorLog": "Pas de date trouvée pour Shotgun."
  },
  {
    "eventPlace": "Shotgun",
    "city": "Lyon",
    "country": "France",
    "isCancelled": false,
    "eventURL": "https://shotgun.live/fr/artists/0riles",
    "eventDetailedStyle": "",
    "eventStyle": "Live",
    "source": {
      "name": "Shotgun",
      "city": "Lyon",
      "country": "France"
    },
    "unixDate": -1,
    "errorLog": "Pas de date trouvée pour Shotgun."
  },
  {
    "eventPlace": "Shotgun",
    "city": "Lyon",
    "country": "France",
    "isCancelled": false,
    "eventURL": "https://shotgun.live/fr/artists/holypriest_music",
    "eventDetailedStyle": "",
    "eventStyle": "Live",
    "source": {
      "name": "Shotgun",
      "city": "Lyon",
      "country": "France"
    },
    "unixDate": -1,
    "errorLog": "Pas de date trouvée pour Shotgun."
  },
  {
    "eventPlace": "Shotgun",
    "city": "Lyon",
    "country": "France",
    "isCancelled": false,
    "eventURL": "https://shotgun.live/fr/artists/lamano19",
    "eventDetailedStyle": "",
    "eventStyle": "Live",
    "source": {
      "name": "Shotgun",
      "city": "Lyon",
      "country": "France"
    },
    "unixDate": -1,
    "errorLog": "Pas de date trouvée pour Shotgun."
  },
  {
    "eventPlace": "Shotgun",
    "city": "Lyon",
    "country": "France",
    "isCancelled": false,
    "eventURL": "https://shotgun.live/fr/venues/nuits-sonores",
    "eventDetailedStyle": "",
    "eventStyle": "Live",
    "source": {
      "name": "Shotgun",
      "city": "Lyon",
      "country": "France"
    },
    "unixDate": -1,
    "errorLog": "Pas de date trouvée pour Shotgun."
  },
  {
    "eventPlace": "Shotgun",
    "city": "Lyon",
    "country": "France",
    "isCancelled": false,
    "eventURL": "https://shotgun.live/fr/venues/23-59",
    "eventDetailedStyle": "",
    "eventStyle": "Live",
    "source": {
      "name": "Shotgun",
      "city": "Lyon",
      "country": "France"
    },
    "unixDate": -1,
    "errorLog": "Pas de date trouvée pour Shotgun."
  },
  {
    "eventPlace": "Shotgun",
    "city": "Lyon",
    "country": "France",
    "isCancelled": false,
    "eventURL": "https://shotgun.live/fr/venues/le-sucre",
    "eventDetailedStyle": "",
    "eventStyle": "Live",
    "source": {
      "name": "Shotgun",
      "city": "Lyon",
      "country": "France"
    },
    "unixDate": -1,
    "errorLog": "Pas de date trouvée pour Shotgun."
  },
  {
    "eventPlace": "Shotgun",
    "city": "Lyon",
    "country": "France",
    "isCancelled": false,
    "eventURL": "https://shotgun.live/fr/venues/encore",
    "eventDetailedStyle": "",
    "eventStyle": "Live",
    "source": {
      "name": "Shotgun",
      "city": "Lyon",
      "country": "France"
    },
    "unixDate": -1,
    "errorLog": "Pas de date trouvée pour Shotgun."
  },
  {
    "eventPlace": "Shotgun",
    "city": "Lyon",
    "country": "France",
    "isCancelled": false,
    "eventURL": "https://shotgun.live/fr/venues/sound-factory",
    "eventDetailedStyle": "",
    "eventStyle": "Live",
    "source": {
      "name": "Shotgun",
      "city": "Lyon",
      "country": "France"
    },
    "unixDate": -1,
    "errorLog": "Pas de date trouvée pour Shotgun."
  },
  {
    "eventPlace": "Shotgun",
    "city": "Lyon",
    "country": "France",
    "isCancelled": false,
    "eventURL": "https://shotgun.live/fr/cities/annecy",
    "eventDetailedStyle": "",
    "eventStyle": "Live",
    "source": {
      "name": "Shotgun",
      "city": "Lyon",
      "country": "France"
    },
    "unixDate": -1,
    "errorLog": "Pas de date trouvée pour Shotgun."
  },
  {
    "eventPlace": "Shotgun",
    "city": "Lyon",
    "country": "France",
    "isCancelled": false,
    "eventURL": "https://shotgun.live/fr/cities/clermont-ferrand",
    "eventDetailedStyle": "",
    "eventStyle": "Live",
    "source": {
      "name": "Shotgun",
      "city": "Lyon",
      "country": "France"
    },
    "unixDate": -1,
    "errorLog": "Pas de date trouvée pour Shotgun."
  },
  {
    "eventPlace": "Shotgun",
    "city": "Lyon",
    "country": "France",
    "isCancelled": false,
    "eventURL": "https://shotgun.live/fr/cities/geneva",
    "eventDetailedStyle": "",
    "eventStyle": "Live",
    "source": {
      "name": "Shotgun",
      "city": "Lyon",
      "country": "France"
    },
    "unixDate": -1,
    "errorLog": "Pas de date trouvée pour Shotgun."
  },
  {
    "eventPlace": "Shotgun",
    "city": "Lyon",
    "country": "France",
    "isCancelled": false,
    "eventURL": "https://shotgun.live/fr/cities/grenoble",
    "eventDetailedStyle": "",
    "eventStyle": "Live",
    "source": {
      "name": "Shotgun",
      "city": "Lyon",
      "country": "France"
    },
    "unixDate": -1,
    "errorLog": "Pas de date trouvée pour Shotgun."
  },
  {
    "eventPlace": "Shotgun",
    "city": "Lyon",
    "country": "France",
    "isCancelled": false,
    "eventURL": "https://shotgun.live/fr/cities/saint-etienne",
    "eventDetailedStyle": "",
    "eventStyle": "Live",
    "source": {
      "name": "Shotgun",
      "city": "Lyon",
      "country": "France"
    },
    "unixDate": -1,
    "errorLog": "Pas de date trouvée pour Shotgun."
  },
  {
    "eventPlace": "Savage",
    "city": "Hanoi",
    "country": "Vietnam",
    "eventDate": "O c t 0 9 T h u",
    "eventName": "Savage Thursday",
    "eventStyle": "Live",
    "isCancelled": false,
    "eventURL": "https://likdo.asia/event/2233",
    "eventDetailedStyle": "",
    "source": {
      "name": "Likdo",
      "city": "Hanoi",
      "country": "Vietnam"
    },
    "unixDate": 0,
    "errorLog": "Format de date invalide pour Likdo. Reçu 'O c t 0 9 T h u', converti en '00-09'. Formats essayés: dd-MM"
  },
  {
    "eventPlace": "Klymax Discotheque",
    "city": "Hanoi",
    "country": "Vietnam",
    "eventDate": "O c t 0 9 T h u",
    "eventName": "Alexander Skancke + Latex",
    "eventStyle": "Live",
    "isCancelled": false,
    "eventURL": "https://likdo.asia/event/2254",
    "eventDetailedStyle": "",
    "source": {
      "name": "Likdo",
      "city": "Hanoi",
      "country": "Vietnam"
    },
    "unixDate": 0,
    "errorLog": "Format de date invalide pour Likdo. Reçu 'O c t 0 9 T h u', converti en '00-09'. Formats essayés: dd-MM"
  },
  {
    "eventPlace": "Savage",
    "city": "Hanoi",
    "country": "Vietnam",
    "eventDate": "O c t 1 0 F r i",
    "eventName": ".TAG OUTDOOR PARTY",
    "eventStyle": "Live",
    "isCancelled": false,
    "eventURL": "https://likdo.asia/event/2234",
    "eventDetailedStyle": "",
    "source": {
      "name": "Likdo",
      "city": "Hanoi",
      "country": "Vietnam"
    },
    "unixDate": 0,
    "errorLog": "Format de date invalide pour Likdo. Reçu 'O c t 1 0 F r i', converti en '01-00'. Formats essayés: dd-MM"
  },
  {
    "eventPlace": "The Observatory",
    "city": "Hanoi",
    "country": "Vietnam",
    "eventDate": "O c t 1 0 F r i",
    "eventName": "Friday 10 October Youss, Special K, Adduc, Unmute Takeover w/ Komga, Lam Dao & Anh Vy",
    "eventStyle": "Live",
    "isCancelled": false,
    "eventURL": "https://likdo.asia/event/2246",
    "eventDetailedStyle": "",
    "source": {
      "name": "Likdo",
      "city": "Hanoi",
      "country": "Vietnam"
    },
    "unixDate": 0,
    "errorLog": "Format de date invalide pour Likdo. Reçu 'O c t 1 0 F r i', converti en '01-00'. Formats essayés: dd-MM"
  },
  {
    "eventPlace": "VENT",
    "city": "Hanoi",
    "country": "Vietnam",
    "eventDate": "O c t 1 0 F r i",
    "eventName": "Bloody",
    "eventStyle": "Live",
    "isCancelled": false,
    "eventURL": "https://likdo.asia/event/2253",
    "eventDetailedStyle": "",
    "source": {
      "name": "Likdo",
      "city": "Hanoi",
      "country": "Vietnam"
    },
    "unixDate": 0,
    "errorLog": "Format de date invalide pour Likdo. Reçu 'O c t 1 0 F r i', converti en '01-00'. Formats essayés: dd-MM"
  },
  {
    "eventPlace": "teller",
    "city": "Hanoi",
    "country": "Vietnam",
    "eventDate": "O c t 1 0 F r i",
    "eventName": "Invites DJ Masda",
    "eventStyle": "Live",
    "isCancelled": false,
    "eventURL": "https://likdo.asia/event/2255",
    "eventDetailedStyle": "",
    "source": {
      "name": "Likdo",
      "city": "Hanoi",
      "country": "Vietnam"
    },
    "unixDate": 0,
    "errorLog": "Format de date invalide pour Likdo. Reçu 'O c t 1 0 F r i', converti en '01-00'. Formats essayés: dd-MM"
  },
  {
    "eventPlace": "Zénith de Saint-Étienne",
    "city": "Saint-Etienne",
    "country": "France",
    "eventName": "LES BODIN’S",
    "eventDate": "05 déc. 2025 | 20:00 06 déc. 2025 | 20:00 07 déc. 2025 | 15:00",
    "isCancelled": false,
    "eventURL": "https://www.zenith-saint-etienne.fr/evenement/les-bodins/",
    "eventDetailedStyle": "",
    "eventStyle": "Live",
    "source": {
      "name": "Zénith de Saint-Étienne",
      "city": "Saint-Etienne",
      "country": "France"
    },
    "unixDate": 0,
    "errorLog": "Format de date invalide pour Zénith de Saint-Étienne. Reçu '05 déc. 2025 | 20:00 06 déc. 2025 | 20:00 07 déc. 2025 | 15:00', converti en '05-12-2025-20:00-06-12-2025-20:00-07-2025-15:00'. Formats essayés: dd-MM-yyyy-HH:mm"
  },
  {
    "eventPlace": "Zénith de Saint-Étienne",
    "city": "Saint-Etienne",
    "country": "France",
    "eventName": "PAT’ PATROUILLE",
    "eventDate": "21 mars 2026 | 14:00 21 mars 2026 | 17:00",
    "isCancelled": false,
    "eventURL": "https://www.zenith-saint-etienne.fr/evenement/pat-patrouille/",
    "eventDetailedStyle": "",
    "eventStyle": "Live",
    "source": {
      "name": "Zénith de Saint-Étienne",
      "city": "Saint-Etienne",
      "country": "France"
    },
    "unixDate": 0,
    "errorLog": "Format de date invalide pour Zénith de Saint-Étienne. Reçu '21 mars 2026 | 14:00 21 mars 2026 | 17:00', converti en '21-03-2026-14:00-21-2026-17:00'. Formats essayés: dd-MM-yyyy-HH:mm"
  },
  {
    "eventPlace": "Zénith de Saint-Étienne",
    "city": "Saint-Etienne",
    "country": "France",
    "eventName": "LE ROI SOLEIL",
    "eventDate": "19 mai 2026 | 20:00 20 mai 2026 | 20:00",
    "isCancelled": false,
    "eventURL": "https://www.zenith-saint-etienne.fr/evenement/le-roi-soleil/",
    "eventDetailedStyle": "",
    "eventStyle": "Live",
    "source": {
      "name": "Zénith de Saint-Étienne",
      "city": "Saint-Etienne",
      "country": "France"
    },
    "unixDate": 0,
    "errorLog": "Format de date invalide pour Zénith de Saint-Étienne. Reçu '19 mai 2026 | 20:00 20 mai 2026 | 20:00', converti en '19-05-2026-20:00-20-2026-20:00'. Formats essayés: dd-MM-yyyy-HH:mm"
  },
  {
    "eventPlace": "Zénith de Saint-Étienne",
    "city": "Saint-Etienne",
    "country": "France",
    "eventName": "DUB INC",
    "eventDate": "05 déc. 2026 | 20:00 06 déc. 2026 | 19:00",
    "isCancelled": false,
    "eventURL": "https://www.zenith-saint-etienne.fr/evenement/dub-inc/",
    "eventDetailedStyle": "",
    "eventStyle": "Live",
    "source": {
      "name": "Zénith de Saint-Étienne",
      "city": "Saint-Etienne",
      "country": "France"
    },
    "unixDate": 0,
    "errorLog": "Format de date invalide pour Zénith de Saint-Étienne. Reçu '05 déc. 2026 | 20:00 06 déc. 2026 | 19:00', converti en '05-12-2026-20:00-06-12-2026-19:00'. Formats essayés: dd-MM-yyyy-HH:mm"
  },
  {
    "eventPlace": "La Belle Electrique",
    "city": "Grenoble",
    "country": "France",
    "eventName": "GIGI FM + LACCHESI + MAZAIR",
    "eventDate": "Du 18.10.25 / 23h55 au 19.10.25 / 5h30",
    "eventStyle": "Electro",
    "eventURL": "https://www.la-belle-electrique.com/fr/agenda/gigifm-lacchesi-mazair",
    "isCancelled": false,
    "eventDetailedStyle": "Techno",
    "source": {
      "name": "La Belle Electrique",
      "city": "Grenoble",
      "country": "France"
    },
    "unixDate": 0,
    "errorLog": "Format de date invalide pour La Belle Electrique. Reçu 'Du 18.10.25 / 23h55 au 19.10.25 / 5h30', converti en '18-10-25-23:55-19-10-25-05:30'. Formats essayés: dd-MM-yy-HH:mm"
  },
  {
    "eventPlace": "La Belle Electrique",
    "city": "Grenoble",
    "country": "France",
    "eventName": "Dressing Club Dub w/ Wise Up Hi-Fi",
    "eventDate": "Du 24.10.25 / 20h au 25.10.25 / 1h",
    "eventStyle": "Gratuit",
    "eventURL": "https://www.la-belle-electrique.com/fr/agenda/dressing-club-dub",
    "isCancelled": false,
    "eventDetailedStyle": "Gratuit",
    "source": {
      "name": "La Belle Electrique",
      "city": "Grenoble",
      "country": "France"
    },
    "unixDate": 0,
    "errorLog": "Format de date invalide pour La Belle Electrique. Reçu 'Du 24.10.25 / 20h au 25.10.25 / 1h', converti en '24-10-25-20:00-25-10-25-01:00'. Formats essayés: dd-MM-yy-HH:mm"
  },
  {
    "eventPlace": "La Belle Electrique",
    "city": "Grenoble",
    "country": "France",
    "eventName": "Dynamita's Night #36 Funky Brasil édition : Rio 77 + Dj Suspect",
    "eventDate": "Du 25.10.25 / 23h au 26.10.25 / 5h",
    "eventStyle": "Rock",
    "eventURL": "https://www.la-belle-electrique.com/fr/agenda/dynamitas-night-36",
    "isCancelled": false,
    "eventDetailedStyle": "Funk",
    "source": {
      "name": "La Belle Electrique",
      "city": "Grenoble",
      "country": "France"
    },
    "unixDate": 0,
    "errorLog": "Format de date invalide pour La Belle Electrique. Reçu 'Du 25.10.25 / 23h au 26.10.25 / 5h', converti en '25-10-25-23:00-26-10-25-05:00'. Formats essayés: dd-MM-yy-HH:mm"
  },
  {
    "eventPlace": "La Belle Electrique",
    "city": "Grenoble",
    "country": "France",
    "eventName": "Dressing Boum #4 • Boum d'Halloween",
    "eventDate": "Du 31.10.25 / 15h au 31.10.25 / 18h",
    "eventStyle": "Gratuit",
    "eventURL": "https://www.la-belle-electrique.com/fr/agenda/dressing-boum-halloween-4",
    "isCancelled": false,
    "eventDetailedStyle": "Gratuit",
    "source": {
      "name": "La Belle Electrique",
      "city": "Grenoble",
      "country": "France"
    },
    "unixDate": 0,
    "errorLog": "Format de date invalide pour La Belle Electrique. Reçu 'Du 31.10.25 / 15h au 31.10.25 / 18h', converti en '31-10-25-15:00-31-10-25-18:00'. Formats essayés: dd-MM-yy-HH:mm"
  },
  {
    "eventPlace": "La Belle Electrique",
    "city": "Grenoble",
    "country": "France",
    "eventName": "Dressing Club • Halloween Party w/ Init1",
    "eventDate": "Du 31.10.25 / 22h30 au 31.10.25 / 1h",
    "eventStyle": "Gratuit",
    "eventURL": "https://www.la-belle-electrique.com/fr/agenda/dressing-club-halloween-party",
    "isCancelled": false,
    "eventDetailedStyle": "Gratuit",
    "source": {
      "name": "La Belle Electrique",
      "city": "Grenoble",
      "country": "France"
    },
    "unixDate": 0,
    "errorLog": "Format de date invalide pour La Belle Electrique. Reçu 'Du 31.10.25 / 22h30 au 31.10.25 / 1h', converti en '31-10-25-22:30-31-10-25-01:00'. Formats essayés: dd-MM-yy-HH:mm"
  },
  {
    "eventPlace": "La Belle Electrique",
    "city": "Grenoble",
    "country": "France",
    "eventName": "COMPLET • Chinese Man Records",
    "eventDate": "Du 08.11.25 / 22h au 09.11.25 / 4h",
    "eventStyle": "Rap",
    "eventURL": "https://www.la-belle-electrique.com/fr/agenda/chinese-man-records",
    "isCancelled": false,
    "eventDetailedStyle": "Hip-hop",
    "source": {
      "name": "La Belle Electrique",
      "city": "Grenoble",
      "country": "France"
    },
    "unixDate": 0,
    "errorLog": "Format de date invalide pour La Belle Electrique. Reçu 'Du 08.11.25 / 22h au 09.11.25 / 4h', converti en '08-11-25-22:00-09-11-25-04:00'. Formats essayés: dd-MM-yy-HH:mm"
  },
  {
    "eventPlace": "La Belle Electrique",
    "city": "Grenoble",
    "country": "France",
    "eventName": "Formation • Les revenus de l'artiste musicien.ne",
    "eventDate": "Du 15.11.25 / 10h au 15.11.25 / 17h",
    "eventStyle": "Live",
    "eventURL": "https://www.la-belle-electrique.com/fr/agenda/formation-revenus-artiste",
    "isCancelled": false,
    "eventDetailedStyle": "",
    "source": {
      "name": "La Belle Electrique",
      "city": "Grenoble",
      "country": "France"
    },
    "unixDate": 0,
    "errorLog": "Format de date invalide pour La Belle Electrique. Reçu 'Du 15.11.25 / 10h au 15.11.25 / 17h', converti en '15-11-25-10:00-15-11-25-17:00'. Formats essayés: dd-MM-yy-HH:mm"
  },
  {
    "eventPlace": "La Belle Electrique",
    "city": "Grenoble",
    "country": "France",
    "eventName": "Los Burritos Santos • Release Party - Nuit de la Cumbia + Chicharron + Kumbia Boruka + DJ Felipe",
    "eventDate": "Du 15.11.25 / 20h au 16.11.25 / 2h",
    "eventStyle": "Cumbia",
    "eventURL": "https://www.la-belle-electrique.com/fr/agenda/los-burritos-release",
    "isCancelled": false,
    "eventDetailedStyle": "Cumbia",
    "source": {
      "name": "La Belle Electrique",
      "city": "Grenoble",
      "country": "France"
    },
    "unixDate": 0,
    "errorLog": "Format de date invalide pour La Belle Electrique. Reçu 'Du 15.11.25 / 20h au 16.11.25 / 2h', converti en '15-11-25-20:00-16-11-25-02:00'. Formats essayés: dd-MM-yy-HH:mm"
  },
  {
    "eventPlace": "La Belle Electrique",
    "city": "Grenoble",
    "country": "France",
    "eventName": "JEN CARDINI b2b PABLO BOZZI + CLEO b2b DJ LIBERT",
    "eventDate": "Du 22.11.25 / 23h55 au 23.11.25 / 5h30",
    "eventStyle": "Electro",
    "eventURL": "https://www.la-belle-electrique.com/fr/agenda/jennifer-cardini-pablo-bozzi-cleo-dj-libert",
    "isCancelled": false,
    "eventDetailedStyle": "Techno",
    "source": {
      "name": "La Belle Electrique",
      "city": "Grenoble",
      "country": "France"
    },
    "unixDate": 0,
    "errorLog": "Format de date invalide pour La Belle Electrique. Reçu 'Du 22.11.25 / 23h55 au 23.11.25 / 5h30', converti en '22-11-25-23:55-23-11-25-05:30'. Formats essayés: dd-MM-yy-HH:mm"
  },
  {
    "eventPlace": "La Belle Electrique",
    "city": "Grenoble",
    "country": "France",
    "eventName": "Formation • L'export : compréhensions, productions et stratégies",
    "eventDate": "Du 29.11.25 / 9h30 au 29.11.25 / 17h30",
    "eventStyle": "Live",
    "eventURL": "https://www.la-belle-electrique.com/fr/agenda/formation-export",
    "isCancelled": false,
    "eventDetailedStyle": "",
    "source": {
      "name": "La Belle Electrique",
      "city": "Grenoble",
      "country": "France"
    },
    "unixDate": 0,
    "errorLog": "Format de date invalide pour La Belle Electrique. Reçu 'Du 29.11.25 / 9h30 au 29.11.25 / 17h30', converti en '29-11-25-09:30-29-11-25-17:30'. Formats essayés: dd-MM-yy-HH:mm"
  },
  {
    "eventPlace": "La Belle Electrique",
    "city": "Grenoble",
    "country": "France",
    "eventName": "AFTRWRK SESSION • ADI SHANKARA + ASHKABAD + DUB DYNASTY FEAT JONAH DAN + ROOTS RAID FEAT SHANTI D",
    "eventDate": "Du 12.12.25 / 22h au 13.12.25 / 4h",
    "eventStyle": "Electro",
    "eventURL": "https://www.la-belle-electrique.com/fr/agenda/aftrwrk-session",
    "isCancelled": false,
    "eventDetailedStyle": "Dub",
    "source": {
      "name": "La Belle Electrique",
      "city": "Grenoble",
      "country": "France"
    },
    "unixDate": 0,
    "errorLog": "Format de date invalide pour La Belle Electrique. Reçu 'Du 12.12.25 / 22h au 13.12.25 / 4h', converti en '12-12-25-22:00-13-12-25-04:00'. Formats essayés: dd-MM-yy-HH:mm"
  },
  {
    "eventPlace": "La Belle Electrique",
    "city": "Grenoble",
    "country": "France",
    "eventName": "THE HACKER INVITE : BELARIA + DJEDJOTRONIC [LIVE] + ENDRIK SCHROEDER",
    "eventDate": "Du 20.12.25 / 23h55 au 21.12.25 / 5h30",
    "eventStyle": "Electro",
    "eventURL": "https://www.la-belle-electrique.com/fr/agenda/the-hacker-belaria-djedjotronic-endrick-schroeder",
    "isCancelled": false,
    "eventDetailedStyle": "Techno",
    "source": {
      "name": "La Belle Electrique",
      "city": "Grenoble",
      "country": "France"
    },
    "unixDate": 0,
    "errorLog": "Format de date invalide pour La Belle Electrique. Reçu 'Du 20.12.25 / 23h55 au 21.12.25 / 5h30', converti en '20-12-25-23:55-21-12-25-05:30'. Formats essayés: dd-MM-yy-HH:mm"
  },
  {
    "eventPlace": "Le Summum",
    "city": "Grenoble",
    "country": "France",
    "eventStyle": "Live",
    "eventName": "Oktoberfest",
    "eventDate": "17 & 18 octobre 2025",
    "isCancelled": false,
    "eventURL": "https://www.summum-grenoble.com/evenements/oktoberfest/",
    "eventDetailedStyle": "Concert",
    "source": {
      "name": "Le Summum",
      "city": "Grenoble",
      "country": "France"
    },
    "unixDate": 0,
    "errorLog": "Format de date invalide pour Le Summum. Reçu '17 & 18 octobre 2025', converti en '17-18-10-2025'. Formats essayés: dd-MM-yyyy"
  },
  {
    "eventPlace": "La Maison Scène",
    "city": "Saint-Etienne",
    "country": "France",
    "eventName": "Dj Guest - Vasco",
    "eventDate": "24",
    "isCancelled": false,
    "eventURL": "https://shotgun.live/fr/events/dj-guest-vasco",
    "eventDetailedStyle": "",
    "eventStyle": "Live",
    "source": {
      "name": "Shotgun_saint-etienne",
      "city": "Saint-Etienne",
      "country": "France"
    },
    "unixDate": 0,
    "errorLog": "Format de date invalide pour Shotgun_saint-etienne. Reçu '24', converti en '24'. Formats essayés: dd-MM-HH:mm"
  },
  {
    "eventPlace": "CEPAC Silo",
    "city": "Marseille",
    "country": "France",
    "eventStyle": "Humour",
    "eventName": "GREG EMPECHE MOI",
    "eventDate": "11 - reporté & 18 oct. 2025 - Annulé",
    "eventURL": "https://www.cepacsilo-marseille.fr/evenement/greg-empeche-moi/",
    "isCancelled": true,
    "eventDetailedStyle": "Humour",
    "source": {
      "name": "CEPAC Silo",
      "city": "Marseille",
      "country": "France"
    },
    "unixDate": 0,
    "errorLog": "Format de date invalide pour CEPAC Silo. Reçu '11 - reporté & 18 oct. 2025 - Annulé', converti en '11-18-10-2025'. Formats essayés: dd-MM-yyyy"
  },
  {
    "eventPlace": "CEPAC Silo",
    "city": "Marseille",
    "country": "France",
    "eventStyle": "Humour",
    "eventName": "Nawell Madani",
    "eventDate": "16 & 17 oct. 2025",
    "eventURL": "https://www.cepacsilo-marseille.fr/evenement/nawell-madani/",
    "isCancelled": false,
    "eventDetailedStyle": "Humour",
    "source": {
      "name": "CEPAC Silo",
      "city": "Marseille",
      "country": "France"
    },
    "unixDate": 0,
    "errorLog": "Format de date invalide pour CEPAC Silo. Reçu '16 & 17 oct. 2025', converti en '16-17-10-2025'. Formats essayés: dd-MM-yyyy"
  },
  {
    "eventPlace": "CEPAC Silo",
    "city": "Marseille",
    "country": "France",
    "eventStyle": "Live",
    "eventName": "SOFIANE PAMART",
    "eventDate": "Du 31 oct. au 2 nov. 2025",
    "eventURL": "https://www.cepacsilo-marseille.fr/evenement/sofiane-pamart/",
    "isCancelled": false,
    "eventDetailedStyle": "Concert",
    "source": {
      "name": "CEPAC Silo",
      "city": "Marseille",
      "country": "France"
    },
    "unixDate": 0,
    "errorLog": "Format de date invalide pour CEPAC Silo. Reçu 'Du 31 oct. au 2 nov. 2025', converti en '31-10-02-11-2025'. Formats essayés: dd-MM-yyyy"
  },
  {
    "eventPlace": "CEPAC Silo",
    "city": "Marseille",
    "country": "France",
    "eventStyle": "Spectacle",
    "eventName": "Stomp",
    "eventDate": "14, 15 & 16 novembre 2025",
    "eventURL": "https://www.cepacsilo-marseille.fr/evenement/stomp/",
    "isCancelled": false,
    "eventDetailedStyle": "Spectacle",
    "source": {
      "name": "CEPAC Silo",
      "city": "Marseille",
      "country": "France"
    },
    "unixDate": 0,
    "errorLog": "Format de date invalide pour CEPAC Silo. Reçu '14, 15 & 16 novembre 2025', converti en '14-15-16-11-2025'. Formats essayés: dd-MM-yyyy"
  },
  {
    "eventPlace": "Théâtre de La Criée",
    "city": "Marseille",
    "country": "France",
    "eventStyle": "Théâtre performance",
    "eventName": "INHALE DELIRIUM EXHALE",
    "eventDate": "10 - 11 octobre 2025",
    "isCancelled": false,
    "eventURL": "https://theatre-lacriee.com/programmation/evenements/inhale-delirium-exhale",
    "eventDetailedStyle": "Théâtre performance",
    "source": {
      "name": "Théâtre de La Criée",
      "city": "Marseille",
      "country": "France"
    },
    "unixDate": 0,
    "errorLog": "Format de date invalide pour Théâtre de La Criée. Reçu '10 - 11 octobre 2025', converti en '10-11-10-2025'. Formats essayés: dd-MM-yyyy"
  },
  {
    "eventPlace": "Théâtre de La Criée",
    "city": "Marseille",
    "country": "France",
    "eventStyle": "Théâtre",
    "eventName": "65 rue d'Aubagne",
    "eventDate": "15 - 17 octobre 2025",
    "isCancelled": false,
    "eventURL": "https://theatre-lacriee.com/programmation/evenements/65-rue-daubagne-a-lastronef",
    "eventDetailedStyle": "Théâtre",
    "source": {
      "name": "Théâtre de La Criée",
      "city": "Marseille",
      "country": "France"
    },
    "unixDate": 0,
    "errorLog": "Format de date invalide pour Théâtre de La Criée. Reçu '15 - 17 octobre 2025', converti en '15-17-10-2025'. Formats essayés: dd-MM-yyyy"
  },
  {
    "eventPlace": "Théâtre de La Criée",
    "city": "Marseille",
    "country": "France",
    "eventStyle": "Théâtre",
    "eventName": "La Stupéfaction",
    "eventDate": "4 - 8 novembre 2025",
    "isCancelled": false,
    "eventURL": "https://theatre-lacriee.com/programmation/evenements/la-stupefaction",
    "eventDetailedStyle": "Théâtre",
    "source": {
      "name": "Théâtre de La Criée",
      "city": "Marseille",
      "country": "France"
    },
    "unixDate": 0,
    "errorLog": "Format de date invalide pour Théâtre de La Criée. Reçu '4 - 8 novembre 2025', converti en '04-08-11-2025'. Formats essayés: dd-MM-yyyy"
  },
  {
    "eventPlace": "Théâtre de La Criée",
    "city": "Marseille",
    "country": "France",
    "eventStyle": "Théâtre",
    "eventName": "65 rue d'Aubagne",
    "eventDate": "6 - 9 novembre 2025",
    "isCancelled": false,
    "eventURL": "https://theatre-lacriee.com/programmation/evenements/65-rue-daubagne-au-theatre-de-loeuvre",
    "eventDetailedStyle": "Théâtre",
    "source": {
      "name": "Théâtre de La Criée",
      "city": "Marseille",
      "country": "France"
    },
    "unixDate": 0,
    "errorLog": "Format de date invalide pour Théâtre de La Criée. Reçu '6 - 9 novembre 2025', converti en '06-09-11-2025'. Formats essayés: dd-MM-yyyy"
  },
  {
    "eventPlace": "Théâtre de La Criée",
    "city": "Marseille",
    "country": "France",
    "eventStyle": "Théâtre jeune public",
    "eventName": "Je suis trop vert",
    "eventDate": "12 - 15 novembre 2025",
    "isCancelled": false,
    "eventURL": "https://theatre-lacriee.com/programmation/evenements/je-suis-trop-vert",
    "eventDetailedStyle": "Théâtre jeune public",
    "source": {
      "name": "Théâtre de La Criée",
      "city": "Marseille",
      "country": "France"
    },
    "unixDate": 0,
    "errorLog": "Format de date invalide pour Théâtre de La Criée. Reçu '12 - 15 novembre 2025', converti en '12-15-11-2025'. Formats essayés: dd-MM-yyyy"
  },
  {
    "eventPlace": "Théâtre de La Criée",
    "city": "Marseille",
    "country": "France",
    "eventStyle": "Théâtre jeune public",
    "eventName": "OKA",
    "eventDate": "13 - 15 novembre 2025",
    "isCancelled": false,
    "eventURL": "https://theatre-lacriee.com/programmation/evenements/oka",
    "eventDetailedStyle": "Théâtre jeune public",
    "source": {
      "name": "Théâtre de La Criée",
      "city": "Marseille",
      "country": "France"
    },
    "unixDate": 0,
    "errorLog": "Format de date invalide pour Théâtre de La Criée. Reçu '13 - 15 novembre 2025', converti en '13-15-11-2025'. Formats essayés: dd-MM-yyyy"
  },
  {
    "eventPlace": "Théâtre de La Criée",
    "city": "Marseille",
    "country": "France",
    "eventStyle": "Théâtre",
    "eventName": "65 rue d'Aubagne",
    "eventDate": "20 - 21 novembre 2025",
    "isCancelled": false,
    "eventURL": "https://theatre-lacriee.com/programmation/evenements/65-rue-daubagne-au-theatre-antoine-vitez",
    "eventDetailedStyle": "Théâtre",
    "source": {
      "name": "Théâtre de La Criée",
      "city": "Marseille",
      "country": "France"
    },
    "unixDate": 0,
    "errorLog": "Format de date invalide pour Théâtre de La Criée. Reçu '20 - 21 novembre 2025', converti en '20-21-11-2025'. Formats essayés: dd-MM-yyyy"
  },
  {
    "eventPlace": "Théâtre de La Criée",
    "city": "Marseille",
    "country": "France",
    "eventStyle": "Théâtre jeune public",
    "eventName": "BABÏL",
    "eventDate": "26 - 29 novembre 2025",
    "isCancelled": false,
    "eventURL": "https://theatre-lacriee.com/programmation/evenements/babil",
    "eventDetailedStyle": "Théâtre jeune public",
    "source": {
      "name": "Théâtre de La Criée",
      "city": "Marseille",
      "country": "France"
    },
    "unixDate": 0,
    "errorLog": "Format de date invalide pour Théâtre de La Criée. Reçu '26 - 29 novembre 2025', converti en '26-29-11-2025'. Formats essayés: dd-MM-yyyy"
  },
  {
    "eventPlace": "Théâtre de La Criée",
    "city": "Marseille",
    "country": "France",
    "eventStyle": "Théâtre",
    "eventName": "LEVIATHAN",
    "eventDate": "28 - 30 novembre 2025",
    "isCancelled": false,
    "eventURL": "https://theatre-lacriee.com/programmation/evenements/leviathan",
    "eventDetailedStyle": "Théâtre",
    "source": {
      "name": "Théâtre de La Criée",
      "city": "Marseille",
      "country": "France"
    },
    "unixDate": 0,
    "errorLog": "Format de date invalide pour Théâtre de La Criée. Reçu '28 - 30 novembre 2025', converti en '28-30-11-2025'. Formats essayés: dd-MM-yyyy"
  },
  {
    "eventPlace": "Théâtre de La Criée",
    "city": "Marseille",
    "country": "France",
    "eventStyle": "Théâtre",
    "eventName": "LACRIMA",
    "eventDate": "10 - 12 décembre 2025",
    "isCancelled": false,
    "eventURL": "https://theatre-lacriee.com/programmation/evenements/lacrima",
    "eventDetailedStyle": "Théâtre",
    "source": {
      "name": "Théâtre de La Criée",
      "city": "Marseille",
      "country": "France"
    },
    "unixDate": 0,
    "errorLog": "Format de date invalide pour Théâtre de La Criée. Reçu '10 - 12 décembre 2025', converti en '10-12-12-2025'. Formats essayés: dd-MM-yyyy"
  },
  {
    "eventPlace": "Théâtre de La Criée",
    "city": "Marseille",
    "country": "France",
    "eventStyle": "Théâtre et philosophie",
    "eventName": "Dire une société désirable 2025",
    "eventDate": "10 - 13 décembre 2025",
    "isCancelled": false,
    "eventURL": "https://theatre-lacriee.com/programmation/evenements/dire-une-societe-desirable",
    "eventDetailedStyle": "Théâtre et philosophie",
    "source": {
      "name": "Théâtre de La Criée",
      "city": "Marseille",
      "country": "France"
    },
    "unixDate": 0,
    "errorLog": "Format de date invalide pour Théâtre de La Criée. Reçu '10 - 13 décembre 2025', converti en '10-13-12-2025'. Formats essayés: dd-MM-yyyy"
  },
  {
    "eventPlace": "Théâtre de La Criée",
    "city": "Marseille",
    "country": "France",
    "eventStyle": "Théâtre",
    "eventName": "L' Hôtel du Libre-Échange",
    "eventDate": "17 - 19 décembre 2025",
    "isCancelled": false,
    "eventURL": "https://theatre-lacriee.com/programmation/evenements/l-hotel-du-libre-echange",
    "eventDetailedStyle": "Théâtre",
    "source": {
      "name": "Théâtre de La Criée",
      "city": "Marseille",
      "country": "France"
    },
    "unixDate": 0,
    "errorLog": "Format de date invalide pour Théâtre de La Criée. Reçu '17 - 19 décembre 2025', converti en '17-19-12-2025'. Formats essayés: dd-MM-yyyy"
  },
  {
    "eventPlace": "Théâtre de La Criée",
    "city": "Marseille",
    "country": "France",
    "eventStyle": "Théâtre",
    "eventName": "65 rue d'Aubagne",
    "eventDate": "14 - 18 janvier 2026",
    "isCancelled": false,
    "eventURL": "https://theatre-lacriee.com/programmation/evenements/65-rue-daubagne",
    "eventDetailedStyle": "Théâtre",
    "source": {
      "name": "Théâtre de La Criée",
      "city": "Marseille",
      "country": "France"
    },
    "unixDate": 0,
    "errorLog": "Format de date invalide pour Théâtre de La Criée. Reçu '14 - 18 janvier 2026', converti en '14-18-01-2026'. Formats essayés: dd-MM-yyyy"
  },
  {
    "eventPlace": "Théâtre de La Criée",
    "city": "Marseille",
    "country": "France",
    "eventStyle": "Théâtre",
    "eventName": "Sorcières (titre provisoire)",
    "eventDate": "22 - 24 janvier 2026",
    "isCancelled": false,
    "eventURL": "https://theatre-lacriee.com/programmation/evenements/sorcieres-titre-provisoire",
    "eventDetailedStyle": "Théâtre",
    "source": {
      "name": "Théâtre de La Criée",
      "city": "Marseille",
      "country": "France"
    },
    "unixDate": 0,
    "errorLog": "Format de date invalide pour Théâtre de La Criée. Reçu '22 - 24 janvier 2026', converti en '22-24-01-2026'. Formats essayés: dd-MM-yyyy"
  },
  {
    "eventPlace": "Théâtre de La Criée",
    "city": "Marseille",
    "country": "France",
    "eventStyle": "Théâtre",
    "eventName": "La Leçon",
    "eventDate": "29 janvier - 13 février 2026",
    "isCancelled": false,
    "eventURL": "https://theatre-lacriee.com/programmation/evenements/la-lecon",
    "eventDetailedStyle": "Théâtre",
    "source": {
      "name": "Théâtre de La Criée",
      "city": "Marseille",
      "country": "France"
    },
    "unixDate": 0,
    "errorLog": "Format de date invalide pour Théâtre de La Criée. Reçu '29 janvier - 13 février 2026', converti en '29-01-13-02-2026'. Formats essayés: dd-MM-yyyy"
  },
  {
    "eventPlace": "Théâtre de La Criée",
    "city": "Marseille",
    "country": "France",
    "eventStyle": "Théâtre",
    "eventName": "Les Généreux / El Ajouad",
    "eventDate": "4 - 7 février 2026",
    "isCancelled": false,
    "eventURL": "https://theatre-lacriee.com/programmation/evenements/les-genereux-el-ajouad",
    "eventDetailedStyle": "Théâtre",
    "source": {
      "name": "Théâtre de La Criée",
      "city": "Marseille",
      "country": "France"
    },
    "unixDate": 0,
    "errorLog": "Format de date invalide pour Théâtre de La Criée. Reçu '4 - 7 février 2026', converti en '04-07-02-2026'. Formats essayés: dd-MM-yyyy"
  },
  {
    "eventPlace": "Théâtre de La Criée",
    "city": "Marseille",
    "country": "France",
    "eventStyle": "Théâtre",
    "eventName": "Chavirer de bord",
    "eventDate": "11 - 13 février 2026",
    "isCancelled": false,
    "eventURL": "https://theatre-lacriee.com/programmation/evenements/chavirer-de-bord",
    "eventDetailedStyle": "Théâtre",
    "source": {
      "name": "Théâtre de La Criée",
      "city": "Marseille",
      "country": "France"
    },
    "unixDate": 0,
    "errorLog": "Format de date invalide pour Théâtre de La Criée. Reçu '11 - 13 février 2026', converti en '11-13-02-2026'. Formats essayés: dd-MM-yyyy"
  },
  {
    "eventPlace": "Théâtre de La Criée",
    "city": "Marseille",
    "country": "France",
    "eventStyle": "Live",
    "eventName": "Alexandre Kantorow",
    "eventDate": "16 - 17 février 2026",
    "isCancelled": false,
    "eventURL": "https://theatre-lacriee.com/programmation/evenements/kantorow",
    "eventDetailedStyle": "Musique",
    "source": {
      "name": "Théâtre de La Criée",
      "city": "Marseille",
      "country": "France"
    },
    "unixDate": 0,
    "errorLog": "Format de date invalide pour Théâtre de La Criée. Reçu '16 - 17 février 2026', converti en '16-17-02-2026'. Formats essayés: dd-MM-yyyy"
  },
  {
    "eventPlace": "Théâtre de La Criée",
    "city": "Marseille",
    "country": "France",
    "eventStyle": "Théâtre et philosophie",
    "eventName": "Dire une société désirable 2026",
    "eventDate": "4 - 6 mars 2026",
    "isCancelled": false,
    "eventURL": "https://theatre-lacriee.com/programmation/evenements/dire-une-societe-desirable-2026",
    "eventDetailedStyle": "Théâtre et philosophie",
    "source": {
      "name": "Théâtre de La Criée",
      "city": "Marseille",
      "country": "France"
    },
    "unixDate": 0,
    "errorLog": "Format de date invalide pour Théâtre de La Criée. Reçu '4 - 6 mars 2026', converti en '04-06-03-2026'. Formats essayés: dd-MM-yyyy"
  },
  {
    "eventPlace": "Théâtre de La Criée",
    "city": "Marseille",
    "country": "France",
    "eventStyle": "Théâtre",
    "eventName": "L'Art de la joie",
    "eventDate": "7 - 8 mars 2026",
    "isCancelled": false,
    "eventURL": "https://theatre-lacriee.com/programmation/evenements/lart-de-la-joie",
    "eventDetailedStyle": "Théâtre",
    "source": {
      "name": "Théâtre de La Criée",
      "city": "Marseille",
      "country": "France"
    },
    "unixDate": 0,
    "errorLog": "Format de date invalide pour Théâtre de La Criée. Reçu '7 - 8 mars 2026', converti en '07-08-03-2026'. Formats essayés: dd-MM-yyyy"
  },
  {
    "eventPlace": "Marseille",
    "city": "Marseille",
    "country": "France",
    "eventName": "Fiesta Des Suds 2025",
    "eventDate": "9",
    "eventStyle": "Live",
    "isCancelled": false,
    "eventURL": "https://shotgun.live/fr/festivals/fiesta-des-suds-2025",
    "eventDetailedStyle": "",
    "source": {
      "name": "Shotgun-marseille",
      "city": "Marseille",
      "country": "France"
    },
    "unixDate": 0,
    "errorLog": "Format de date invalide pour Shotgun-marseille. Reçu '9', converti en '09'. Formats essayés: dd-MM-HH:mm"
  },
  {
    "eventPlace": "Espace Julien",
    "city": "Marseille",
    "country": "France",
    "eventDate": "",
    "eventName": "HERMAN DUNE",
    "eventStyle": "Chanson",
    "isCancelled": false,
    "eventURL": "https://espace-julien.com/agenda/herman-dune",
    "eventDetailedStyle": "Complet Folk",
    "source": {
      "name": "Espace Julien",
      "city": "Marseille",
      "country": "France"
    },
    "unixDate": 0,
    "errorLog": "Format de date invalide pour Espace Julien. Reçu '', converti en ''. Formats essayés: dd-MM-HH:mm"
  },
  {
    "eventPlace": "⁠L'Affranchi",
    "city": "Marseille",
    "country": "France",
    "eventName": "SOUFFRANCE",
    "eventDate": "sam 08 nov 20 h 00 min 23 h 30 min SOUFFRANCE",
    "isCancelled": false,
    "eventDetailedStyle": "",
    "eventStyle": "Live",
    "source": {
      "name": "⁠L'Affranchi",
      "city": "Marseille",
      "country": "France"
    },
    "unixDate": 0,
    "errorLog": "Format de date invalide pour ⁠L'Affranchi. Reçu 'sam 08 nov 20 h 00 min 23 h 30 min SOUFFRANCE', converti en '08-11-20-00-23-30'. Formats essayés: dd-MM-yyyy"
  },
  {
    "eventPlace": "Centre culturel L'Ilyade",
    "city": "Marseille",
    "country": "France",
    "eventStyle": "Exposition",
    "eventName": "Mémoires tissées",
    "eventURL": "https://www.lilyade.fr/evenements/memoires-tissees/",
    "eventDate": "vendredi 14 novembre 2025",
    "isCancelled": false,
    "eventDetailedStyle": "Exposition",
    "source": {
      "name": "Centre culturel L'Ilyade",
      "city": "Marseille",
      "country": "France"
    },
    "unixDate": 0,
    "errorLog": "Format de date invalide pour Centre culturel L'Ilyade. Reçu 'vendredi 14 novembre 2025', converti en '14-11-2025'. Formats essayés: dd-MM-yyyy-HH:mm"
  },
  {
    "eventPlace": "Zénith de Dijon",
    "city": "Dijon",
    "country": "France",
    "eventStyle": "Live",
    "eventName": "Indochine",
    "eventDate": "Du 29 oct. au 1 nov. 2025",
    "eventURL": "https://www.zenith-dijon.fr/evenement/indochine/",
    "isCancelled": false,
    "eventDetailedStyle": "Concert",
    "source": {
      "name": "Zénith de Dijon",
      "city": "Dijon",
      "country": "France"
    },
    "unixDate": 0,
    "errorLog": "Format de date invalide pour Zénith de Dijon. Reçu 'Du 29 oct. au 1 nov. 2025', converti en '29-10-01-11-2025'. Formats essayés: dd-MM-yyyy"
  },
  {
    "eventPlace": "Zénith de Dijon",
    "city": "Dijon",
    "country": "France",
    "eventStyle": "Spectacle",
    "eventName": "Les Bodin’s",
    "eventDate": "28, 29 & 30 novembre 2025",
    "eventURL": "https://www.zenith-dijon.fr/evenement/les-bodins/",
    "isCancelled": false,
    "eventDetailedStyle": "Spectacle",
    "source": {
      "name": "Zénith de Dijon",
      "city": "Dijon",
      "country": "France"
    },
    "unixDate": 0,
    "errorLog": "Format de date invalide pour Zénith de Dijon. Reçu '28, 29 & 30 novembre 2025', converti en '28-29-30-11-2025'. Formats essayés: dd-MM-yyyy"
  },
  {
    "eventPlace": "L'Olympia",
    "city": "Paris",
    "country": "France",
    "eventName": "Jean-Paul Rouve",
    "eventDate": "13-14 oct. 2025",
    "isCancelled": true,
    "eventURL": "https://www.olympiahall.com/agenda/jean-paul-rouve/",
    "eventDetailedStyle": "",
    "eventStyle": "Live",
    "source": {
      "name": "L'Olympia",
      "city": "Paris",
      "country": "France"
    },
    "unixDate": 0,
    "errorLog": "Format de date invalide pour L'Olympia. Reçu '13-14 oct. 2025', converti en '13-14-10-2025'. Formats essayés: dd-MM-yyyy"
  },
  {
    "eventPlace": "L'Olympia",
    "city": "Paris",
    "country": "France",
    "eventName": "Ethel Cain",
    "eventDate": "18-19 oct. 2025",
    "isCancelled": false,
    "eventURL": "https://www.olympiahall.com/agenda/ethel-cain/",
    "eventDetailedStyle": "",
    "eventStyle": "Live",
    "source": {
      "name": "L'Olympia",
      "city": "Paris",
      "country": "France"
    },
    "unixDate": 0,
    "errorLog": "Format de date invalide pour L'Olympia. Reçu '18-19 oct. 2025', converti en '18-19-10-2025'. Formats essayés: dd-MM-yyyy"
  },
  {
    "eventPlace": "L'Olympia",
    "city": "Paris",
    "country": "France",
    "eventName": "Patti Smith and her band perform horses",
    "eventDate": "20-21 oct. 2025",
    "isCancelled": false,
    "eventURL": "https://www.olympiahall.com/agenda/patti-smith-and-her-band-perform-horses/",
    "eventDetailedStyle": "",
    "eventStyle": "Live",
    "source": {
      "name": "L'Olympia",
      "city": "Paris",
      "country": "France"
    },
    "unixDate": 0,
    "errorLog": "Format de date invalide pour L'Olympia. Reçu '20-21 oct. 2025', converti en '20-21-10-2025'. Formats essayés: dd-MM-yyyy"
  }
]